LICENSE
README.md
setup.cfg
setup.py
pytextclassifier/__init__.py
pytextclassifier/base_classifier.py
pytextclassifier/bert_classfication_utils.py
pytextclassifier/bert_classification_model.py
pytextclassifier/bert_classifier.py
pytextclassifier/bert_multi_label_classification_model.py
pytextclassifier/classic_classifier.py
pytextclassifier/data_helper.py
pytextclassifier/fasttext_classifier.py
pytextclassifier/stopwords.txt
pytextclassifier/textcluster.py
pytextclassifier/textcnn_classifier.py
pytextclassifier/textrnn_classifier.py
pytextclassifier/time_util.py
pytextclassifier/tokenizer.py
pytextclassifier.egg-info/PKG-INFO
pytextclassifier.egg-info/SOURCES.txt
pytextclassifier.egg-info/dependency_links.txt
pytextclassifier.egg-info/requires.txt
pytextclassifier.egg-info/top_level.txt
pytextclassifier/../examples/thucnews_train_1w.txt