Metadata-Version: 2.1
Name: pytextclassifier
Version: 1.3.9
Summary: Text Classifier, Text Classification
Home-page: https://github.com/shibing624/pytextclassifier
Author: XuMing
Author-email: xuming624@qq.com
License: Apache 2.0
Keywords: pytextclassifier,textclassifier,classifier,textclassification
Classifier: Intended Audience :: Science/Research
Classifier: Operating System :: OS Independent
Classifier: License :: OSI Approved :: Apache Software License
Classifier: Programming Language :: Python
Classifier: Programming Language :: Python :: 2.7
Classifier: Programming Language :: Python :: 3
Classifier: Topic :: Text Processing :: Linguistic
Classifier: Topic :: Scientific/Engineering :: Artificial Intelligence
License-File: LICENSE
